init_equation/__init__.py
init_equation/__main__.py
init_equation/chapters.py
init_equation/choice_option.py
init_equation/equation.py
init_equation/main.py
init_equation-0.1.6.dist-info/METADATA
init_equation-0.1.6.dist-info/WHEEL
init_equation-0.1.6.dist-info/entry_points.txt
init_equation-0.1.6.dist-info/RECORD
