Metadata-Version: 2.1
Name: init-equation
Version: 0.1.6
Summary: Added qrcode lines in main.py for main.tex
Author: vaibhavblayer
Author-email: vaibhavblayer@gmail.com
Requires-Python: >=3.11,<4.0
Classifier: Programming Language :: Python :: 3
Classifier: Programming Language :: Python :: 3.11
